mteam/__init__.py
mteam/client.py
mteam/config.py
mteam/core.py
mteam/exceptions.py
mteam/models.py
mteam/member/__init__.py
mteam/member/client.py
mteam/member/models.py
mteam/subtitle/__init__.py
mteam/subtitle/client.py
mteam/subtitle/models.py
mteam/torrent/__init__.py
mteam/torrent/client.py
mteam/torrent/models.py
mteam-0.1.5.dist-info/METADATA
mteam-0.1.5.dist-info/WHEEL
mteam-0.1.5.dist-info/top_level.txt
mteam-0.1.5.dist-info/RECORD
