Metadata-Version: 2.4
Name: mteam
Version: 0.1.5
Summary: M-TEAM API SDK
Author-email: amintong <min.tong.cn@gmail.com>
License: MIT
Project-URL: Homepage, https://github.com/amintong/mteam-python
Requires-Python: >=3.7
Requires-Dist: httpx>=0.22.0
Requires-Dist: pydantic~=1.10.22
Requires-Dist: python-dotenv>=0.19.0
Requires-Dist: email-validator>=1.30
